satori_rtm_cli/__init__.py
satori_rtm_cli-1.5.3.dist-info/DESCRIPTION.rst
satori_rtm_cli-1.5.3.dist-info/METADATA
satori_rtm_cli-1.5.3.dist-info/RECORD
satori_rtm_cli-1.5.3.dist-info/WHEEL
satori_rtm_cli-1.5.3.dist-info/entry_points.txt
satori_rtm_cli-1.5.3.dist-info/metadata.json
satori_rtm_cli-1.5.3.dist-info/top_level.txt
